multicollections/__init__.py
multicollections/_typing.py
multicollections/abc.py
multicollections/py.typed
multicollections-1.0.6.dist-info/licenses/LICENSE.txt
multicollections-1.0.6.dist-info/WHEEL
multicollections-1.0.6.dist-info/METADATA
multicollections-1.0.6.dist-info/RECORD
