Metadata-Version: 2.4
Name: multicollections
Version: 1.0.6
Summary: Fully generic MultiDict class
Author: Gabriel S. Gerlero
Author-email: Gabriel S. Gerlero <ggerlero@cimec.unl.edu.ar>
License-Expression: Apache-2.0
License-File: LICENSE.txt
Classifier: Development Status :: 5 - Production/Stable
Classifier: Intended Audience :: Developers
Classifier: License :: OSI Approved :: Apache Software License
Classifier: Programming Language :: Python
Classifier: Programming Language :: Python :: 3
Classifier: Programming Language :: Python :: 3.8
Classifier: Programming Language :: Python :: 3.9
Classifier: Programming Language :: Python :: 3.10
Classifier: Programming Language :: Python :: 3.11
Classifier: Programming Language :: Python :: 3.12
Classifier: Programming Language :: Python :: 3.13
Classifier: Programming Language :: Python :: 3.14
Classifier: Topic :: Software Development :: Libraries
Classifier: Typing :: Typed
Classifier: Operating System :: OS Independent
Requires-Python: >=3.8
Project-URL: Documentation, https://multicollections.readthedocs.io
Project-URL: Homepage, https://github.com/gerlero/multicollections
Project-URL: Repository, https://github.com/gerlero/multicollections
